CHANGES.rst
MANIFEST.in
README.rst
setup.py
versions.cfg
src/shoobx/__init__.py
src/shoobx.flowview.egg-info/PKG-INFO
src/shoobx.flowview.egg-info/SOURCES.txt
src/shoobx.flowview.egg-info/dependency_links.txt
src/shoobx.flowview.egg-info/entry_points.txt
src/shoobx.flowview.egg-info/namespace_packages.txt
src/shoobx.flowview.egg-info/not-zip-safe
src/shoobx.flowview.egg-info/requires.txt
src/shoobx.flowview.egg-info/top_level.txt
src/shoobx/flowview/__init__.py
src/shoobx/flowview/cli.py
src/shoobx/flowview/flowview.css
src/shoobx/flowview/flowview.js
src/shoobx/flowview/layout.xslt
src/shoobx/flowview/xpdl.py
src/shoobx/flowview/xpdl.xslt
src/shoobx/flowview/tests/__init__.py
src/shoobx/flowview/tests/test_xpdl.py
src/shoobx/flowview/tests/samples/external.xpdl
src/shoobx/flowview/tests/samples/samples.xpdl