Metadata-Version: 1.1
Name: shoobx.flowview
Version: 1.0.0
Summary: XPDL Viewer and Browser
Home-page: UNKNOWN
Author: Shoobx, Inc.
Author-email: dev@shoobx.com
License: Proprietary
Keywords: xpdl process workflow
Platform: UNKNOWN
Classifier: Development Status :: 2 - Pre-Alpha
Classifier: Intended Audience :: Developers
Classifier: Programming Language :: Python
Classifier: Programming Language :: Python :: 2
Classifier: Programming Language :: Python :: 2.7
Classifier: Programming Language :: Python :: 3
Classifier: Programming Language :: Python :: 3.5
Classifier: Programming Language :: Python :: 3.6
Classifier: Programming Language :: Python :: Implementation :: CPython
Classifier: Programming Language :: Python :: Implementation :: PyPy
Classifier: Natural Language :: English
Classifier: Operating System :: OS Independent
